odmantic_fernet_field/__init__.py
odmantic_fernet_field/env.py
odmantic_fernet_field/fernet_field.py
odmantic_fernet_field/utils.py
odmantic_fernet_field_type-0.0.4.dist-info/METADATA
odmantic_fernet_field_type-0.0.4.dist-info/WHEEL
odmantic_fernet_field_type-0.0.4.dist-info/entry_points.txt
odmantic_fernet_field_type-0.0.4.dist-info/top_level.txt
odmantic_fernet_field_type-0.0.4.dist-info/RECORD
