Metadata-Version: 2.4
Name: odmantic-fernet-field-type
Version: 0.0.4
Summary: A field type that encrypts values using Fernet symmetric encryption.
Author-email: Arnab Jain <arnab@inocentum.in>
License-Expression: MIT
Project-URL: Homepage, https://github.com/arnabJ/ODMantic-Fernet-Field-Type
Project-URL: Bug Tracker, https://github.com/arnabJ/ODMantic-Fernet-Field-Type/issues
Project-URL: Source, https://github.com/arnabJ/ODMantic-Fernet-Field-Type
Project-URL: Changelog, https://github.com/arnabJ/ODMantic-Fernet-Field-Type/releases
Project-URL: Documentation, https://github.com/arnabJ/ODMantic-Fernet-Field-Type/blob/main/README.md
Classifier: Programming Language :: Python
Classifier: Programming Language :: Python :: 3
Classifier: Programming Language :: Python :: 3 :: Only
Classifier: Programming Language :: Python :: 3.9
Classifier: Programming Language :: Python :: 3.10
Classifier: Programming Language :: Python :: 3.11
Classifier: Programming Language :: Python :: 3.12
Classifier: Programming Language :: Python :: 3.13
Classifier: Intended Audience :: Developers
Classifier: Intended Audience :: Information Technology
Classifier: Intended Audience :: System Administrators
Classifier: Operating System :: OS Independent
Classifier: Topic :: Software Development :: Libraries :: Python Modules
Classifier: Topic :: Internet
Requires-Python: >=3.9
Requires-Dist: odmantic>=1.0.2
Requires-Dist: python-dotenv>=1.0.1
Requires-Dist: cryptography>=44.0.2
